fedoo/.DS_Store
fedoo/__init__.py
fedoo/_version.py
fedoo/constitutivelaw/__init__.py
fedoo/constitutivelaw/beam.py
fedoo/constitutivelaw/cohesivelaw.py
fedoo/constitutivelaw/cohesivelaw_mod.py
fedoo/constitutivelaw/composite_ud.py
fedoo/constitutivelaw/elastic_anisotropic.py
fedoo/constitutivelaw/elastic_isotrop.py
fedoo/constitutivelaw/elastic_orthotropic.py
fedoo/constitutivelaw/elasto_plasticity.py
fedoo/constitutivelaw/fe2.py
fedoo/constitutivelaw/heterogeneous.py
fedoo/constitutivelaw/shell.py
fedoo/constitutivelaw/simcoon_umat.py
fedoo/constitutivelaw/spring.py
fedoo/constitutivelaw/thermal_prop.py
fedoo/constitutivelaw/viso_elastic_orthotropic.py
fedoo/constraint/__init__.py
fedoo/constraint/contact.py
fedoo/constraint/distributed_load.py
fedoo/constraint/periodic_bc.py
fedoo/constraint/rigid_tie.py
fedoo/core/__init__.py
fedoo/core/_sparsematrix.py
fedoo/core/assembly.py
fedoo/core/assembly_sum.py
fedoo/core/base.py
fedoo/core/boundary_conditions.py
fedoo/core/dataset.py
fedoo/core/diffop.py
fedoo/core/mechanical3d.py
fedoo/core/mesh.py
fedoo/core/modelingspace.py
fedoo/core/output.py
fedoo/core/problem.py
fedoo/core/weakform.py
fedoo/homogen/__init__.py
fedoo/homogen/tangent_stiffness.py
fedoo/lib_elements/__init__.py
fedoo/lib_elements/beam.py
fedoo/lib_elements/cohesive.py
fedoo/lib_elements/element_base.py
fedoo/lib_elements/element_list.py
fedoo/lib_elements/finite_difference_1d.py
fedoo/lib_elements/hexahedron.py
fedoo/lib_elements/incompressible.py
fedoo/lib_elements/line.py
fedoo/lib_elements/plate.py
fedoo/lib_elements/quadrangle.py
fedoo/lib_elements/tetrahedron.py
fedoo/lib_elements/triangle.py
fedoo/lib_elements/wedge.py
fedoo/mesh/__init__.py
fedoo/mesh/functions.py
fedoo/mesh/importmesh.py
fedoo/mesh/simple.py
fedoo/mesh/structured_mesh.py
fedoo/pgd/AssemblyPGD.py
fedoo/pgd/MeshPGD.py
fedoo/pgd/PeriodicBoundaryConditionPGD.py
fedoo/pgd/ProblemPGD.py
fedoo/pgd/SeparatedArray.py
fedoo/pgd/SeparatedOperator.py
fedoo/pgd/UsualFunctions.py
fedoo-0.6.1.dist-info/licenses/LICENSE
fedoo-0.6.1.dist-info/METADATA
fedoo-0.6.1.dist-info/WHEEL
fedoo-0.6.1.dist-info/top_level.txt
fedoo-0.6.1.dist-info/RECORD
