Metadata-Version: 2.4
Name: fedoo
Version: 0.6.1
Summary: Finite elements library
Author-email: 3MAH <set3mah@gmail.com>
License: GPLv3
Project-URL: Documentation, https://fedoo.readthedocs.io/en/latest/
Project-URL: Bug Tracker, https://github.com/3MAH/fedoo/issues
Project-URL: Source Code, https://github.com/3MAH/fedoo
Keywords: FEM,Structural mechanics
Classifier: Intended Audience :: Science/Research
Classifier: Topic :: Scientific/Engineering :: Information Analysis
Classifier: Operating System :: Microsoft :: Windows
Classifier: Operating System :: POSIX
Classifier: Operating System :: MacOS
Classifier: Programming Language :: Python :: 3.10
Classifier: Programming Language :: Python :: 3.11
Classifier: Programming Language :: Python :: 3.12
Classifier: Programming Language :: Python :: 3.13
Requires-Python: >=3.10
License-File: LICENSE
Requires-Dist: numpy>=1.26
Requires-Dist: scipy
Provides-Extra: all
Requires-Dist: fedoo[dataio,plot,solver,test]; extra == "all"
Provides-Extra: solver
Requires-Dist: pypardiso; (platform_machine != "arm64" and platform_machine != "aarch64") and extra == "solver"
Requires-Dist: scikit-umfpack; (platform_machine == "arm64" or platform_machine == "aarch64") and extra == "solver"
Provides-Extra: plot
Requires-Dist: matplotlib; extra == "plot"
Requires-Dist: pyvista[io]; extra == "plot"
Provides-Extra: dataio
Requires-Dist: pandas; extra == "dataio"
Provides-Extra: test
Requires-Dist: pytest; extra == "test"
Requires-Dist: pytest-cov; extra == "test"
Provides-Extra: other
Requires-Dist: microgen; extra == "other"
Requires-Dist: simcoon; extra == "other"
Dynamic: license-file
